[
  {
    "label": "Global colors",
    "name": "global_colors",
    "type": "group",
    "children": [
      {
        "label": "Primary",
        "name": "primary",
        "type": "color",
        "visibility": {
          "hidden_subfields": {
            "opacity": true
          }
        },
        "alternate_names": [
          "primary_color"
        ],
        "display_width": null,
        "locked": false,
        "required": false,
        "inherited_value": {},
        "default": {
          "color": "#0b42ff"
        }
      },
      {
        "label": "Primary dark",
        "name": "primary_dark",
        "type": "color",
        "visibility": {
          "hidden_subfields": {
            "opacity": true
          }
        },
        "display_width": null,
        "locked": false,
        "required": false,
        "inherited_value": {},
        "default": {
          "color": "#031040"
        }
      },
      {
        "label": "Secondary",
        "name": "secondary",
        "type": "color",
        "visibility": {
          "hidden_subfields": {
            "opacity": true
          }
        },
        "alternate_names": [
          "secondary_color"
        ],
        "display_width": null,
        "locked": false,
        "required": false,
        "inherited_value": {},
        "default": {
          "color": "#E7ECFF"
        }
      },
      {
        "label": "Warning",
        "name": "warning",
        "type": "color",
        "visibility": {
          "hidden_subfields": {
            "opacity": true
          }
        },
        "display_width": null,
        "locked": false,
        "required": false,
        "inherited_value": {},
        "default": {
          "color": "#ffc107"
        }
      },
      {
        "label": "Global font color",
        "name": "global_font_color",
        "type": "color",
        "visibility": {
          "hidden_subfields": {
            "opacity": true
          }
        },
        "display_width": null,
        "locked": false,
        "required": false,
        "inherited_value": {},
        "default": {
          "color": "#000"
        }
      }
    ],
    "display_width": null,
    "locked": false,
    "tab": "CONTENT",
    "expanded": false,
    "required": false
  },
  {
    "label": "Global fonts",
    "name": "global_fonts",
    "type": "group",
    "children": [
      {
        "label": "Primary",
        "name": "primary",
        "type": "font",
        "visibility": {
          "hidden_subfields": {
            "size": true,
            "styles": true
          }
        },
        "alternate_names": [
          "body_font"
        ],
        "display_width": null,
        "load_external_fonts": true,
        "locked": false,
        "required": false,
        "inherited_value": {
          "property_value_paths": {
            "color": "theme.global_colors.global_font_color.color"
          }
        },
        "default": {
          "fallback": "sans-serif",
          "font": "Iter",
          "font_set": "GOOGLE"
        }
      },
      {
        "label": "Secondary",
        "name": "secondary",
        "type": "font",
        "visibility": {
          "hidden_subfields": {
            "size": true,
            "styles": true
          }
        },
        "alternate_names": [
          "heading_font"
        ],
        "display_width": null,
        "load_external_fonts": true,
        "locked": false,
        "required": false,
        "inherited_value": {
          "property_value_paths": {
            "color": "theme.global_colors.global_font_color.color"
          }
        },
        "default": {
          "fallback": "serif",
          "font": "Montserrat",
          "font_set": "GOOGLE"
        }
      }
    ],
    "display_width": null,
    "locked": false,
    "tab": "CONTENT",
    "expanded": false,
    "required": false
  },
  {
    "label": "Spacing",
    "name": "spacing",
    "type": "group",
    "children": [
      {
        "label": "Vertical spacing",
        "name": "vertical_spacing",
        "type": "number",
        "display": "slider",
        "max": 500,
        "display_width": null,
        "locked": false,
        "step": 1,
        "suffix": "px",
        "min": 0,
        "required": false,
        "default": 80
      }
    ],
    "display_width": null,
    "locked": false,
    "tab": "CONTENT",
    "expanded": false,
    "required": false
  },
  {
    "label": "Text",
    "name": "text",
    "type": "group",
    "children": [
      {
        "label": "Heading one (H1)",
        "name": "h1",
        "type": "group",
        "children": [
          {
            "label": "Font",
            "name": "font",
            "type": "font",
            "display_width": null,
            "load_external_fonts": true,
            "locked": false,
            "required": false,
            "inherited_value": {
              "property_value_paths": {
                "color": "theme.global_fonts.secondary.color",
                "fallback": "theme.global_fonts.secondary.fallback",
                "font": "theme.global_fonts.secondary.font",
                "font_set": "theme.global_fonts.secondary.font_set"
              }
            },
            "default": {
              "size": 50,
              "size_unit": "px",
              "styles": {
                "text-decoration": "none"
              },
              "variant": "700"
            }
          },
          {
            "label": "Transform",
            "name": "transform",
            "type": "choice",
            "display": "select",
            "reordering_enabled": true,
            "display_width": null,
            "locked": false,
            "multiple": false,
            "choices": [
              [
                "none",
                "None"
              ],
              [
                "capitalize",
                "Capitalize"
              ],
              [
                "uppercase",
                "Uppercase"
              ],
              [
                "lowercase",
                "Lowercase"
              ]
            ],
            "preset": null,
            "required": false,
            "default": "none"
          }
        ],
        "display_width": null,
        "locked": false,
        "tab": "CONTENT",
        "expanded": false,
        "required": false
      },
      {
        "label": "Heading two (H2)",
        "name": "h2",
        "type": "group",
        "children": [
          {
            "label": "Font",
            "name": "font",
            "type": "font",
            "display_width": null,
            "load_external_fonts": true,
            "locked": false,
            "required": false,
            "inherited_value": {
              "property_value_paths": {
                "color": "theme.global_fonts.secondary.color",
                "fallback": "theme.global_fonts.secondary.fallback",
                "font": "theme.global_fonts.secondary.font",
                "font_set": "theme.global_fonts.secondary.font_set"
              }
            },
            "default": {
              "size": 38,
              "size_unit": "px",
              "styles": {
                "text-decoration": "none"
              },
              "variant": "700"
            }
          },
          {
            "label": "Transform",
            "name": "transform",
            "type": "choice",
            "display": "select",
            "reordering_enabled": true,
            "display_width": null,
            "locked": false,
            "multiple": false,
            "choices": [
              [
                "none",
                "None"
              ],
              [
                "capitalize",
                "Capitalize"
              ],
              [
                "uppercase",
                "Uppercase"
              ],
              [
                "lowercase",
                "Lowercase"
              ]
            ],
            "preset": null,
            "required": false,
            "default": "none"
          }
        ],
        "display_width": null,
        "locked": false,
        "tab": "CONTENT",
        "expanded": false,
        "required": false
      },
      {
        "label": "Heading three (H3)",
        "name": "h3",
        "type": "group",
        "children": [
          {
            "label": "Font",
            "name": "font",
            "type": "font",
            "display_width": null,
            "load_external_fonts": true,
            "locked": false,
            "required": false,
            "inherited_value": {
              "property_value_paths": {
                "color": "theme.global_fonts.secondary.color",
                "fallback": "theme.global_fonts.secondary.fallback",
                "font": "theme.global_fonts.secondary.font",
                "font_set": "theme.global_fonts.secondary.font_set"
              }
            },
            "default": {
              "size": 30,
              "size_unit": "px",
              "styles": {
                "text-decoration": "none"
              },
              "variant": "700"
            }
          },
          {
            "label": "Transform",
            "name": "transform",
            "type": "choice",
            "display": "select",
            "reordering_enabled": true,
            "display_width": null,
            "locked": false,
            "multiple": false,
            "choices": [
              [
                "none",
                "None"
              ],
              [
                "capitalize",
                "Capitalize"
              ],
              [
                "uppercase",
                "Uppercase"
              ],
              [
                "lowercase",
                "Lowercase"
              ]
            ],
            "preset": null,
            "required": false,
            "default": "none"
          }
        ],
        "display_width": null,
        "locked": false,
        "tab": "CONTENT",
        "expanded": false,
        "required": false
      },
      {
        "label": "Heading four (H4)",
        "name": "h4",
        "type": "group",
        "children": [
          {
            "label": "Font",
            "name": "font",
            "type": "font",
            "display_width": null,
            "load_external_fonts": true,
            "locked": false,
            "required": false,
            "inherited_value": {
              "property_value_paths": {
                "color": "theme.global_fonts.secondary.color",
                "fallback": "theme.global_fonts.secondary.fallback",
                "font": "theme.global_fonts.secondary.font",
                "font_set": "theme.global_fonts.secondary.font_set"
              }
            },
            "default": {
              "size": 24,
              "size_unit": "px",
              "styles": {
                "text-decoration": "none"
              }
            }
          },
          {
            "label": "Transform",
            "name": "transform",
            "type": "choice",
            "display": "select",
            "reordering_enabled": true,
            "display_width": null,
            "locked": false,
            "multiple": false,
            "choices": [
              [
                "none",
                "None"
              ],
              [
                "capitalize",
                "Capitalize"
              ],
              [
                "uppercase",
                "Uppercase"
              ],
              [
                "lowercase",
                "Lowercase"
              ]
            ],
            "preset": null,
            "required": false,
            "default": "none"
          }
        ],
        "display_width": null,
        "locked": false,
        "tab": "CONTENT",
        "expanded": false,
        "required": false
      },
      {
        "label": "Heading five (H5)",
        "name": "h5",
        "type": "group",
        "children": [
          {
            "label": "Font",
            "name": "font",
            "type": "font",
            "display_width": null,
            "load_external_fonts": true,
            "locked": false,
            "required": false,
            "inherited_value": {
              "property_value_paths": {
                "fallback": "theme.global_fonts.secondary.fallback",
                "font": "theme.global_fonts.secondary.font",
                "font_set": "theme.global_fonts.secondary.font_set"
              }
            },
            "default": {
              "color": "#000000",
              "size": 16,
              "size_unit": "px",
              "styles": {
                "text-decoration": "none"
              }
            }
          },
          {
            "label": "Transform",
            "name": "transform",
            "type": "choice",
            "display": "select",
            "reordering_enabled": true,
            "display_width": null,
            "locked": false,
            "multiple": false,
            "choices": [
              [
                "none",
                "None"
              ],
              [
                "capitalize",
                "Capitalize"
              ],
              [
                "uppercase",
                "Uppercase"
              ],
              [
                "lowercase",
                "Lowercase"
              ]
            ],
            "preset": null,
            "required": false,
            "default": "none"
          }
        ],
        "display_width": null,
        "locked": false,
        "tab": "CONTENT",
        "expanded": false,
        "required": false
      },
      {
        "label": "Heading six (H6)",
        "name": "h6",
        "type": "group",
        "children": [
          {
            "label": "Font",
            "name": "font",
            "type": "font",
            "display_width": null,
            "load_external_fonts": true,
            "locked": false,
            "required": false,
            "inherited_value": {
              "property_value_paths": {
                "color": "theme.global_fonts.secondary.color",
                "fallback": "theme.global_fonts.secondary.fallback",
                "font": "theme.global_fonts.secondary.font",
                "font_set": "theme.global_fonts.secondary.font_set"
              }
            },
            "default": {
              "size": 14,
              "size_unit": "px",
              "styles": {
                "text-decoration": "none"
              }
            }
          },
          {
            "label": "Transform",
            "name": "transform",
            "type": "choice",
            "display": "select",
            "reordering_enabled": true,
            "display_width": null,
            "locked": false,
            "multiple": false,
            "choices": [
              [
                "none",
                "None"
              ],
              [
                "capitalize",
                "Capitalize"
              ],
              [
                "uppercase",
                "Uppercase"
              ],
              [
                "lowercase",
                "Lowercase"
              ]
            ],
            "preset": null,
            "required": false,
            "default": "none"
          }
        ],
        "display_width": null,
        "locked": false,
        "tab": "CONTENT",
        "expanded": false,
        "required": false
      },
      {
        "label": "Body",
        "name": "body_font",
        "type": "group",
        "children": [
          {
            "label": "Font",
            "name": "font",
            "type": "font",
            "visibility": {
              "hidden_subfields": {
                "styles": true
              }
            },
            "display_width": null,
            "load_external_fonts": true,
            "locked": false,
            "required": false,
            "inherited_value": {
              "property_value_paths": {
                "color": "theme.global_fonts.primary.color",
                "fallback": "theme.global_fonts.primary.fallback",
                "font": "theme.global_fonts.primary.font",
                "font_set": "theme.global_fonts.primary.font_set"
              }
            },
            "default": {
              "size": 16,
              "size_unit": "px"
            }
          }
        ],
        "display_width": null,
        "locked": false,
        "tab": "CONTENT",
        "expanded": false,
        "required": false
      },
      {
        "label": "Links",
        "name": "links",
        "type": "group",
        "children": [
          {
            "label": "Font",
            "name": "font",
            "type": "font",
            "visibility": {
              "hidden_subfields": {
                "size": true
              }
            },
            "display_width": null,
            "load_external_fonts": true,
            "locked": false,
            "required": false,
            "inherited_value": {
              "property_value_paths": {
                "fallback": "theme.global_fonts.primary.fallback",
                "font": "theme.global_fonts.primary.font",
                "font_set": "theme.global_fonts.primary.font_set"
              }
            },
            "default": {
              "styles": {
                "text-decoration": "underline"
              }
            }
          },
          {
            "label": "Color",
            "name": "color",
            "type": "color",
            "display_width": null,
            "locked": false,
            "required": false,
            "inherited_value": {
              "property_value_paths": {
                "color": "theme.global_colors.primary.color"
              }
            },
            "default": {
              "opacity": 100
            }
          }
        ],
        "display_width": null,
        "locked": false,
        "tab": "CONTENT",
        "expanded": false,
        "required": false
      }
    ],
    "display_width": null,
    "locked": false,
    "tab": "CONTENT",
    "expanded": false,
    "required": false
  },
  {
    "label": "Buttons",
    "name": "buttons",
    "type": "group",
    "children": [
      {
        "label": "Text",
        "name": "text",
        "type": "group",
        "children": [
          {
            "label": "Font",
            "name": "font",
            "type": "font",
            "display_width": null,
            "load_external_fonts": true,
            "locked": false,
            "required": false,
            "inherited_value": {
              "property_value_paths": {
                "fallback": "theme.global_fonts.primary.fallback",
                "font": "theme.global_fonts.primary.font",
                "font_set": "theme.global_fonts.primary.font_set"
              }
            },
            "default": {
              "color": "#FFFFFF",
              "size": 18,
              "size_unit": "px"
            }
          },
          {
            "label": "Transform",
            "name": "transform",
            "type": "choice",
            "display": "select",
            "reordering_enabled": true,
            "display_width": null,
            "locked": false,
            "multiple": false,
            "choices": [
              [
                "none",
                "None"
              ],
              [
                "capitalize",
                "Capitalize"
              ],
              [
                "uppercase",
                "Uppercase"
              ],
              [
                "lowercase",
                "Lowercase"
              ]
            ],
            "preset": null,
            "required": false,
            "default": "none"
          }
        ],
        "display_width": null,
        "locked": false,
        "tab": "CONTENT",
        "expanded": false,
        "required": false
      },
      {
        "label": "Background",
        "name": "background",
        "type": "group",
        "children": [
          {
            "label": "Color",
            "name": "color",
            "type": "color",
            "display_width": null,
            "locked": false,
            "required": false,
            "inherited_value": {
              "property_value_paths": {
                "color": "theme.global_colors.primary.color"
              }
            },
            "default": {
              "opacity": 100
            }
          }
        ],
        "display_width": null,
        "locked": false,
        "tab": "CONTENT",
        "expanded": false,
        "required": false
      },
      {
        "label": "Border",
        "name": "border",
        "type": "group",
        "children": [
          {
            "label": "Border",
            "name": "border",
            "type": "border",
            "allow_custom_border_sides": false,
            "display_width": null,
            "locked": false,
            "required": false,
            "inherited_value": {
              "property_value_paths": {
                "bottom.color": "theme.buttons.background.color.color",
                "left.color": "theme.buttons.background.color.color",
                "right.color": "theme.buttons.background.color.color",
                "top.color": "theme.buttons.background.color.color"
              }
            },
            "default": {
              "top": {
                "width": {
                  "value": 0,
                  "units": "px"
                },
                "opacity": 100,
                "style": "solid",
                "color": "#494A52"
              },
              "right": {
                "width": {
                  "value": 0,
                  "units": "px"
                },
                "opacity": 100,
                "style": "solid",
                "color": "#494A52"
              },
              "bottom": {
                "width": {
                  "value": 0,
                  "units": "px"
                },
                "opacity": 100,
                "style": "solid",
                "color": "#494A52"
              },
              "left": {
                "width": {
                  "value": 0,
                  "units": "px"
                },
                "opacity": 100,
                "style": "solid",
                "color": "#494A52"
              }
            }
          }
        ],
        "display_width": null,
        "locked": false,
        "tab": "CONTENT",
        "expanded": false,
        "required": false
      },
      {
        "label": "Corner",
        "name": "corner",
        "type": "group",
        "children": [
          {
            "label": "Radius",
            "name": "radius",
            "type": "number",
            "display": "text",
            "max": 100,
            "display_width": null,
            "locked": false,
            "step": 1,
            "suffix": "px",
            "required": false,
            "default": 10
          }
        ],
        "display_width": null,
        "locked": false,
        "tab": "CONTENT",
        "expanded": false,
        "required": false
      },
      {
        "label": "Spacing",
        "name": "spacing",
        "type": "group",
        "children": [
          {
            "label": "Spacing",
            "name": "spacing",
            "type": "spacing",
            "visibility": {
              "hidden_subfields": {
                "margin": true
              }
            },
            "display_width": null,
            "locked": false,
            "required": false,
            "default": {
              "padding": {
                "top": {
                  "value": 18,
                  "units": "px"
                },
                "right": {
                  "value": 24,
                  "units": "px"
                },
                "bottom": {
                  "value": 18,
                  "units": "px"
                },
                "left": {
                  "value": 24,
                  "units": "px"
                }
              }
            }
          }
        ],
        "display_width": null,
        "locked": false,
        "tab": "CONTENT",
        "expanded": false,
        "required": false
      },
      {
        "label": "Hover",
        "name": "hover",
        "type": "group",
        "children": [
          {
            "label": "Text",
            "name": "text",
            "type": "group",
            "children": [
              {
                "label": "Color",
                "name": "color",
                "type": "color",
                "display_width": null,
                "locked": false,
                "required": false,
                "default": {
                  "color": "#ffffff",
                  "opacity": 100
                }
              }
            ],
            "display_width": null,
            "locked": false,
            "tab": "CONTENT",
            "expanded": false,
            "required": false
          },
          {
            "label": "Background",
            "name": "background",
            "type": "group",
            "children": [
              {
                "label": "Color",
                "name": "color",
                "type": "color",
                "display_width": null,
                "locked": false,
                "required": false,
                "inherited_value": {
                  "property_value_paths": {
                    "color": "theme.global_colors.primary_dark.color"
                  }
                },
                "default": {
                  "opacity": 100
                }
              }
            ],
            "display_width": null,
            "locked": false,
            "tab": "CONTENT",
            "expanded": false,
            "required": false
          },
          {
            "label": "Border",
            "name": "border",
            "type": "group",
            "children": [
              {
                "label": "Border",
                "name": "border",
                "type": "border",
                "allow_custom_border_sides": false,
                "display_width": null,
                "locked": false,
                "required": false,
                "default": {
                  "top": {
                    "width": {
                      "value": 1,
                      "units": "px"
                    },
                    "opacity": 100,
                    "style": "solid",
                    "color": "#1a334e"
                  },
                  "right": {
                    "width": {
                      "value": 1,
                      "units": "px"
                    },
                    "opacity": 100,
                    "style": "solid",
                    "color": "#1a334e"
                  },
                  "bottom": {
                    "width": {
                      "value": 1,
                      "units": "px"
                    },
                    "opacity": 100,
                    "style": "solid",
                    "color": "#1a334e"
                  },
                  "left": {
                    "width": {
                      "value": 1,
                      "units": "px"
                    },
                    "opacity": 100,
                    "style": "solid",
                    "color": "#1a334e"
                  }
                }
              }
            ],
            "display_width": null,
            "locked": false,
            "tab": "CONTENT",
            "expanded": false,
            "required": false
          },
          {
            "label": "Corner",
            "name": "corner",
            "type": "group",
            "children": [
              {
                "label": "Radius",
                "name": "radius",
                "type": "number",
                "display": "text",
                "max": 100,
                "display_width": null,
                "locked": false,
                "step": 1,
                "suffix": "px",
                "required": false,
                "default": 6
              }
            ],
            "display_width": null,
            "locked": false,
            "tab": "CONTENT",
            "expanded": false,
            "required": false
          }
        ],
        "display_width": null,
        "locked": false,
        "tab": "CONTENT",
        "expanded": false,
        "required": false
      }
    ],
    "display_width": null,
    "locked": false,
    "tab": "CONTENT",
    "expanded": false,
    "required": false
  },
  {
    "label": "Forms",
    "name": "forms",
    "type": "group",
    "children": [
      {
        "label": "Title",
        "name": "title",
        "type": "group",
        "children": [
          {
            "label": "Background",
            "name": "background",
            "type": "group",
            "children": [
              {
                "label": "Color",
                "name": "color",
                "type": "color",
                "display_width": null,
                "locked": false,
                "required": false,
                "inherited_value": {
                  "property_value_paths": {
                    "color": "theme.global_colors.secondary.color"
                  }
                },
                "default": {
                  "opacity": 100
                }
              }
            ],
            "display_width": null,
            "locked": false,
            "tab": "CONTENT",
            "expanded": false,
            "required": false
          },
          {
            "label": "Text",
            "name": "text",
            "type": "group",
            "children": [
              {
                "label": "Font",
                "name": "font",
                "type": "font",
                "display_width": null,
                "load_external_fonts": true,
                "locked": false,
                "required": false,
                "inherited_value": {
                  "property_value_paths": {
                    "color": "theme.global_fonts.secondary.color",
                    "font": "theme.global_fonts.secondary.font",
                    "font_set": "theme.global_fonts.secondary.font_set",
                    "size": "theme.text.h3.font.size",
                    "variant": "theme.text.h3.font.variant"
                  }
                },
                "default": {
                  "size_unit": "px",
                  "styles": {}
                }
              }
            ],
            "display_width": null,
            "locked": false,
            "tab": "CONTENT",
            "expanded": false,
            "required": false
          },
          {
            "label": "Border",
            "name": "border",
            "type": "group",
            "children": [
              {
                "label": "Border",
                "name": "border",
                "type": "border",
                "allow_custom_border_sides": true,
                "display_width": null,
                "locked": false,
                "required": false,
                "inherited_value": {
                  "property_value_paths": {
                    "bottom.color": "theme.forms.title.background.color.color",
                    "left.color": "theme.forms.title.background.color.color",
                    "right.color": "theme.forms.title.background.color.color",
                    "top.color": "theme.forms.title.background.color.color"
                  }
                },
                "default": {
                  "top": {
                    "width": {
                      "value": 1,
                      "units": "px"
                    },
                    "opacity": 100,
                    "style": "none",
                    "color": "#516747"
                  },
                  "right": {
                    "width": {
                      "value": 1,
                      "units": "px"
                    },
                    "opacity": 100,
                    "style": "none",
                    "color": "#516747"
                  },
                  "bottom": {
                    "width": {
                      "value": 1,
                      "units": "px"
                    },
                    "opacity": 100,
                    "style": "none",
                    "color": "#516747"
                  },
                  "left": {
                    "width": {
                      "value": 1,
                      "units": "px"
                    },
                    "opacity": 100,
                    "style": "none",
                    "color": "#516747"
                  }
                }
              }
            ],
            "display_width": null,
            "locked": false,
            "tab": "CONTENT",
            "expanded": false,
            "required": false
          },
          {
            "label": "Spacing",
            "name": "spacing",
            "type": "group",
            "children": [
              {
                "label": "Spacing",
                "name": "spacing",
                "type": "spacing",
                "visibility": {
                  "hidden_subfields": {
                    "margin": true
                  }
                },
                "display_width": null,
                "locked": false,
                "required": false,
                "default": {
                  "padding": {
                    "top": {
                      "value": 0,
                      "units": "px"
                    },
                    "right": {
                      "value": 0,
                      "units": "px"
                    },
                    "bottom": {
                      "value": 30,
                      "units": "px"
                    },
                    "left": {
                      "value": 0,
                      "units": "px"
                    }
                  }
                }
              }
            ],
            "display_width": null,
            "locked": false,
            "tab": "CONTENT",
            "expanded": false,
            "required": false
          },
          {
            "label": "Corner",
            "name": "corner",
            "type": "group",
            "children": [
              {
                "label": "Top Left Radius",
                "name": "top_left_radius",
                "type": "number",
                "display": "text",
                "max": 100,
                "display_width": null,
                "locked": false,
                "step": 1,
                "suffix": "px",
                "required": false,
                "default": 0
              },
              {
                "label": "Top Right Radius",
                "name": "top_right_radius",
                "type": "number",
                "display": "text",
                "max": 100,
                "display_width": null,
                "locked": false,
                "step": 1,
                "suffix": "px",
                "required": false,
                "default": 0
              },
              {
                "label": "Bottom Left Radius",
                "name": "bottom_left_radius",
                "type": "number",
                "display": "text",
                "max": 100,
                "display_width": null,
                "locked": false,
                "step": 1,
                "suffix": "px",
                "required": false,
                "default": 0
              },
              {
                "label": "Bottom Right Radius",
                "name": "bottom_right_radius",
                "type": "number",
                "display": "text",
                "max": 100,
                "display_width": null,
                "locked": false,
                "step": 1,
                "suffix": "px",
                "required": false,
                "default": 0
              }
            ],
            "display_width": null,
            "locked": false,
            "tab": "CONTENT",
            "expanded": false,
            "required": false
          }
        ],
        "display_width": null,
        "locked": false,
        "tab": "CONTENT",
        "expanded": false,
        "required": false
      },
      {
        "label": "Labels",
        "name": "labels",
        "type": "group",
        "children": [
          {
            "label": "Text",
            "name": "text",
            "type": "group",
            "children": [
              {
                "label": "Color",
                "name": "color",
                "type": "color",
                "visibility": {
                  "hidden_subfields": {
                    "opacity": true
                  }
                },
                "display_width": null,
                "locked": false,
                "required": false,
                "inherited_value": {
                  "property_value_paths": {
                    "color": "theme.global_fonts.primary.color"
                  }
                },
                "default": {
                  "color": null,
                  "opacity": null
                }
              }
            ],
            "display_width": null,
            "locked": false,
            "tab": "CONTENT",
            "expanded": false,
            "required": false
          }
        ],
        "display_width": null,
        "locked": false,
        "tab": "CONTENT",
        "expanded": false,
        "required": false
      },
      {
        "label": "Help text",
        "name": "help_text",
        "type": "group",
        "children": [
          {
            "label": "Text",
            "name": "text",
            "type": "group",
            "children": [
              {
                "label": "Color",
                "name": "color",
                "type": "color",
                "visibility": {
                  "hidden_subfields": {
                    "opacity": true
                  }
                },
                "display_width": null,
                "locked": false,
                "required": false,
                "inherited_value": {
                  "property_value_paths": {
                    "color": "theme.global_fonts.primary.color"
                  }
                },
                "default": {
                  "color": null,
                  "opacity": null
                }
              }
            ],
            "display_width": null,
            "locked": false,
            "tab": "CONTENT",
            "expanded": false,
            "required": false
          }
        ],
        "display_width": null,
        "locked": false,
        "tab": "CONTENT",
        "expanded": false,
        "required": false
      },
      {
        "label": "Fields",
        "name": "fields",
        "type": "group",
        "children": [
          {
            "label": "Placeholder",
            "name": "placeholder",
            "type": "group",
            "children": [
              {
                "label": "Color",
                "name": "color",
                "type": "color",
                "visibility": {
                  "hidden_subfields": {
                    "opacity": true
                  }
                },
                "display_width": null,
                "locked": false,
                "required": false,
                "inherited_value": {
                  "property_value_paths": {
                    "color": "theme.global_fonts.primary.color"
                  }
                },
                "default": {
                  "color": null,
                  "opacity": null
                }
              }
            ],
            "display_width": null,
            "locked": false,
            "tab": "CONTENT",
            "expanded": false,
            "required": false
          },
          {
            "label": "Text",
            "name": "text",
            "type": "group",
            "children": [
              {
                "label": "Color",
                "name": "color",
                "type": "color",
                "visibility": {
                  "hidden_subfields": {
                    "opacity": true
                  }
                },
                "display_width": null,
                "locked": false,
                "required": false,
                "inherited_value": {
                  "property_value_paths": {
                    "color": "theme.global_fonts.primary.color"
                  }
                },
                "default": {
                  "color": null,
                  "opacity": null
                }
              }
            ],
            "display_width": null,
            "locked": false,
            "tab": "CONTENT",
            "expanded": false,
            "required": false
          },
          {
            "label": "Background",
            "name": "background",
            "type": "group",
            "children": [
              {
                "label": "Color",
                "name": "color",
                "type": "color",
                "display_width": null,
                "locked": false,
                "required": false,
                "default": {
                  "color": "#FFFFFF",
                  "opacity": 100
                }
              }
            ],
            "display_width": null,
            "locked": false,
            "tab": "CONTENT",
            "expanded": false,
            "required": false
          },
          {
            "label": "Border",
            "name": "border",
            "type": "group",
            "children": [
              {
                "label": "Border",
                "name": "border",
                "type": "border",
                "allow_custom_border_sides": false,
                "display_width": null,
                "locked": false,
                "required": false,
                "default": {
                  "top": {
                    "width": {
                      "value": 2,
                      "units": "px"
                    },
                    "opacity": 100,
                    "style": "solid",
                    "color": "#D1D6DC"
                  },
                  "right": {
                    "width": {
                      "value": 2,
                      "units": "px"
                    },
                    "opacity": 100,
                    "style": "solid",
                    "color": "#D1D6DC"
                  },
                  "bottom": {
                    "width": {
                      "value": 2,
                      "units": "px"
                    },
                    "opacity": 100,
                    "style": "solid",
                    "color": "#D1D6DC"
                  },
                  "left": {
                    "width": {
                      "value": 2,
                      "units": "px"
                    },
                    "opacity": 100,
                    "style": "solid",
                    "color": "#D1D6DC"
                  }
                }
              }
            ],
            "display_width": null,
            "locked": false,
            "tab": "CONTENT",
            "expanded": false,
            "required": false
          },
          {
            "label": "Corner",
            "name": "corner",
            "type": "group",
            "children": [
              {
                "label": "Radius",
                "name": "radius",
                "type": "number",
                "display": "text",
                "max": 100,
                "display_width": null,
                "locked": false,
                "step": 1,
                "suffix": "px",
                "required": false,
                "default": 3
              }
            ],
            "display_width": null,
            "locked": false,
            "tab": "CONTENT",
            "expanded": false,
            "required": false
          }
        ],
        "display_width": null,
        "locked": false,
        "tab": "CONTENT",
        "expanded": false,
        "required": false
      },
      {
        "label": "Button",
        "name": "button",
        "type": "group",
        "children": [
          {
            "label": "Text",
            "name": "text",
            "type": "group",
            "children": [
              {
                "label": "Font",
                "name": "font",
                "type": "font",
                "validation_regex": "",
                "display_width": null,
                "load_external_fonts": true,
                "locked": false,
                "required": false,
                "inherited_value": {
                  "property_value_paths": {
                    "fallback": "theme.global_fonts.primary.fallback",
                    "font": "theme.global_fonts.primary.font",
                    "font_set": "theme.global_fonts.primary.font_set"
                  }
                },
                "default": {
                  "color": "#FFFFFF",
                  "size": 22,
                  "size_unit": "px"
                }
              }
            ],
            "display_width": null,
            "locked": false,
            "tab": "CONTENT",
            "expanded": false,
            "required": false
          },
          {
            "label": "Border",
            "name": "border",
            "type": "group",
            "children": [
              {
                "label": "Border",
                "name": "border",
                "type": "border",
                "allow_custom_border_sides": false,
                "display_width": null,
                "locked": false,
                "required": false,
                "inherited_value": {
                  "property_value_paths": {
                    "bottom.color": "theme.global_colors.primary.color",
                    "left.color": "theme.global_colors.primary.color",
                    "right.color": "theme.global_colors.primary.color",
                    "top.color": "theme.global_colors.primary.color"
                  }
                },
                "default": {
                  "top": {
                    "width": {
                      "value": 1,
                      "units": "px"
                    },
                    "opacity": 100,
                    "style": "none"
                  },
                  "right": {
                    "width": {
                      "value": 1,
                      "units": "px"
                    },
                    "opacity": 100,
                    "style": "none"
                  },
                  "bottom": {
                    "width": {
                      "value": 1,
                      "units": "px"
                    },
                    "opacity": 100,
                    "style": "none"
                  },
                  "left": {
                    "width": {
                      "value": 1,
                      "units": "px"
                    },
                    "opacity": 100,
                    "style": "none"
                  }
                }
              }
            ],
            "display_width": null,
            "locked": false,
            "tab": "CONTENT",
            "expanded": false,
            "required": false
          },
          {
            "label": "Background",
            "name": "background",
            "type": "group",
            "children": [
              {
                "label": "Color",
                "name": "color",
                "type": "color",
                "display_width": null,
                "locked": false,
                "required": false,
                "inherited_value": {
                  "property_value_paths": {
                    "color": "theme.global_colors.primary.color"
                  }
                },
                "default": {
                  "opacity": 100
                }
              }
            ],
            "display_width": null,
            "locked": false,
            "tab": "CONTENT",
            "expanded": false,
            "required": false
          },
          {
            "label": "Spacing",
            "name": "spacing",
            "type": "group",
            "children": [
              {
                "label": "Spacing",
                "name": "spacing",
                "type": "spacing",
                "visibility": {
                  "hidden_subfields": {
                    "margin": true
                  }
                },
                "display_width": null,
                "locked": false,
                "required": false,
                "inherited_value": {
                  "property_value_paths": {
                    "padding": "theme.buttons.spacing.spacing.padding"
                  }
                },
                "default": {
                  "padding": {
                    "top": {
                      "value": 0,
                      "units": "px"
                    },
                    "right": {
                      "value": 0,
                      "units": "px"
                    },
                    "bottom": {
                      "value": 0,
                      "units": "px"
                    },
                    "left": {
                      "value": 0,
                      "units": "px"
                    }
                  }
                }
              }
            ],
            "display_width": null,
            "locked": false,
            "tab": "CONTENT",
            "expanded": false,
            "required": false
          },
          {
            "label": "Hover",
            "name": "hover",
            "type": "group",
            "children": [
              {
                "label": "Background",
                "name": "background",
                "type": "group",
                "children": [
                  {
                    "label": "Color",
                    "name": "color",
                    "type": "color",
                    "display_width": null,
                    "locked": false,
                    "required": false,
                    "inherited_value": {
                      "property_value_paths": {
                        "color": "theme.global_colors.primary_dark.color"
                      }
                    },
                    "default": {
                      "opacity": 100
                    }
                  }
                ],
                "display_width": null,
                "locked": false,
                "tab": "CONTENT",
                "expanded": false,
                "required": false
              },
              {
                "label": "Border",
                "name": "border",
                "type": "group",
                "children": [
                  {
                    "label": "Border",
                    "name": "border",
                    "type": "border",
                    "allow_custom_border_sides": false,
                    "display_width": null,
                    "locked": false,
                    "required": false,
                    "default": {
                      "top": {
                        "width": {
                          "value": 1,
                          "units": "px"
                        },
                        "color": "#1a334e",
                        "opacity": 100,
                        "style": "none"
                      },
                      "right": {
                        "width": {
                          "value": 1,
                          "units": "px"
                        },
                        "color": "#1a334e",
                        "opacity": 100,
                        "style": "none"
                      },
                      "bottom": {
                        "width": {
                          "value": 1,
                          "units": "px"
                        },
                        "color": "#1a334e",
                        "opacity": 100,
                        "style": "none"
                      },
                      "left": {
                        "width": {
                          "value": 1,
                          "units": "px"
                        },
                        "color": "#1a334e",
                        "opacity": 100,
                        "style": "none"
                      }
                    }
                  }
                ],
                "display_width": null,
                "locked": false,
                "tab": "CONTENT",
                "expanded": false,
                "required": false
              },
              {
                "label": "Text",
                "name": "text",
                "type": "group",
                "children": [
                  {
                    "label": "Color",
                    "name": "color",
                    "type": "color",
                    "visibility": {
                      "hidden_subfields": {
                        "opacity": true
                      }
                    },
                    "display_width": null,
                    "locked": false,
                    "required": false,
                    "default": {
                      "color": "#ffffff"
                    }
                  }
                ],
                "display_width": null,
                "locked": false,
                "tab": "CONTENT",
                "expanded": false,
                "required": false
              }
            ],
            "display_width": null,
            "locked": false,
            "tab": "CONTENT",
            "expanded": false,
            "required": false
          },
          {
            "label": "Focus",
            "name": "focus",
            "type": "group",
            "children": [
              {
                "label": "Background",
                "name": "background",
                "type": "group",
                "children": [
                  {
                    "label": "Color",
                    "name": "color",
                    "type": "color",
                    "display_width": null,
                    "locked": false,
                    "required": false,
                    "inherited_value": {
                      "property_value_paths": {
                        "color": "theme.global_colors.primary_dark.color"
                      }
                    },
                    "default": {
                      "opacity": 100
                    }
                  }
                ],
                "display_width": null,
                "locked": false,
                "tab": "CONTENT",
                "expanded": false,
                "required": false
              },
              {
                "label": "Border",
                "name": "border",
                "type": "group",
                "children": [
                  {
                    "label": "Border",
                    "name": "border",
                    "type": "border",
                    "allow_custom_border_sides": false,
                    "display_width": null,
                    "locked": false,
                    "required": false,
                    "default": {
                      "top": {
                        "width": {
                          "value": 1,
                          "units": "px"
                        },
                        "color": "#1a334e",
                        "opacity": 100,
                        "style": "none"
                      },
                      "right": {
                        "width": {
                          "value": 1,
                          "units": "px"
                        },
                        "color": "#1a334e",
                        "opacity": 100,
                        "style": "none"
                      },
                      "bottom": {
                        "width": {
                          "value": 1,
                          "units": "px"
                        },
                        "color": "#1a334e",
                        "opacity": 100,
                        "style": "none"
                      },
                      "left": {
                        "width": {
                          "value": 1,
                          "units": "px"
                        },
                        "color": "#1a334e",
                        "opacity": 100,
                        "style": "none"
                      }
                    }
                  }
                ],
                "display_width": null,
                "locked": false,
                "tab": "CONTENT",
                "expanded": false,
                "required": false
              },
              {
                "label": "Text",
                "name": "text",
                "type": "group",
                "children": [
                  {
                    "label": "Color",
                    "name": "color",
                    "type": "color",
                    "visibility": {
                      "hidden_subfields": {
                        "opacity": true
                      }
                    },
                    "display_width": null,
                    "locked": false,
                    "required": false,
                    "default": {
                      "color": "#ffffff"
                    }
                  }
                ],
                "display_width": null,
                "locked": false,
                "tab": "CONTENT",
                "expanded": false,
                "required": false
              }
            ],
            "display_width": null,
            "locked": false,
            "tab": "CONTENT",
            "expanded": false,
            "required": false
          }
        ],
        "display_width": null,
        "locked": false,
        "tab": "CONTENT",
        "expanded": false,
        "required": false
      },
      {
        "label": "Form",
        "name": "form",
        "type": "group",
        "children": [
          {
            "label": "Background",
            "name": "background",
            "type": "group",
            "children": [
              {
                "label": "Color",
                "name": "color",
                "type": "color",
                "display_width": null,
                "locked": false,
                "required": false,
                "inherited_value": {
                  "property_value_paths": {
                    "color": "theme.global_colors.secondary.color"
                  }
                },
                "default": {
                  "opacity": 100
                }
              }
            ],
            "display_width": null,
            "locked": false,
            "tab": "CONTENT",
            "expanded": false,
            "required": false
          },
          {
            "label": "Spacing",
            "name": "spacing",
            "type": "group",
            "children": [
              {
                "label": "Spacing",
                "name": "spacing",
                "type": "spacing",
                "visibility": {
                  "hidden_subfields": {
                    "margin": true
                  }
                },
                "display_width": null,
                "locked": false,
                "required": false,
                "default": {
                  "padding": {
                    "top": {
                      "value": 0,
                      "units": "px"
                    },
                    "right": {
                      "value": 0,
                      "units": "px"
                    },
                    "bottom": {
                      "value": 0,
                      "units": "px"
                    },
                    "left": {
                      "value": 0,
                      "units": "px"
                    }
                  }
                }
              }
            ],
            "display_width": null,
            "locked": false,
            "tab": "CONTENT",
            "expanded": false,
            "required": false
          },
          {
            "label": "Border",
            "name": "border",
            "type": "group",
            "children": [
              {
                "label": "Border",
                "name": "border",
                "type": "border",
                "allow_custom_border_sides": true,
                "display_width": null,
                "locked": false,
                "required": false,
                "inherited_value": {
                  "property_value_paths": {
                    "bottom.color": "theme.forms.form.background.color.color",
                    "left.color": "theme.forms.form.background.color.color",
                    "right.color": "theme.forms.form.background.color.color",
                    "top.color": "theme.forms.form.background.color.color"
                  }
                },
                "default": {
                  "top": {
                    "width": {
                      "value": 1,
                      "units": "px"
                    },
                    "opacity": 100,
                    "style": "none",
                    "color": "#f4f0ec"
                  },
                  "right": {
                    "width": {
                      "value": 1,
                      "units": "px"
                    },
                    "opacity": 100,
                    "style": "none",
                    "color": "#f4f0ec"
                  },
                  "bottom": {
                    "width": {
                      "value": 1,
                      "units": "px"
                    },
                    "opacity": 100,
                    "style": "none",
                    "color": "#f4f0ec"
                  },
                  "left": {
                    "width": {
                      "value": 1,
                      "units": "px"
                    },
                    "opacity": 100,
                    "style": "none",
                    "color": "#f4f0ec"
                  }
                }
              }
            ],
            "display_width": null,
            "locked": false,
            "tab": "CONTENT",
            "expanded": false,
            "required": false
          },
          {
            "label": "Corner",
            "name": "corner",
            "type": "group",
            "children": [
              {
                "label": "Top Left Radius",
                "name": "top_left_radius",
                "type": "number",
                "display": "text",
                "max": 100,
                "display_width": null,
                "locked": false,
                "step": 1,
                "suffix": "px",
                "required": false,
                "default": 0
              },
              {
                "label": "Top Right Radius",
                "name": "top_right_radius",
                "type": "number",
                "display": "text",
                "max": 100,
                "display_width": null,
                "locked": false,
                "step": 1,
                "suffix": "px",
                "required": false,
                "default": 0
              },
              {
                "label": "Bottom Left Radius",
                "name": "bottom_left_radius",
                "type": "number",
                "display": "text",
                "max": 100,
                "display_width": null,
                "locked": false,
                "step": 1,
                "suffix": "px",
                "required": false,
                "default": 0
              },
              {
                "label": "Bottom Right Radius",
                "name": "bottom_right_radius",
                "type": "number",
                "display": "text",
                "max": 100,
                "display_width": null,
                "locked": false,
                "step": 1,
                "suffix": "px",
                "required": false,
                "default": 0
              }
            ],
            "display_width": null,
            "locked": false,
            "tab": "CONTENT",
            "expanded": false,
            "required": false
          }
        ],
        "display_width": null,
        "locked": false,
        "tab": "CONTENT",
        "expanded": false,
        "required": false
      }
    ],
    "display_width": null,
    "locked": false,
    "tab": "CONTENT",
    "expanded": false,
    "required": false
  },
  {
    "label": "Tables",
    "name": "tables",
    "type": "group",
    "children": [
      {
        "label": "Header",
        "name": "header",
        "type": "group",
        "children": [
          {
            "label": "Text",
            "name": "text",
            "type": "group",
            "children": [
              {
                "label": "Color",
                "name": "color",
                "type": "color",
                "visibility": {
                  "hidden_subfields": {
                    "opacity": true
                  }
                },
                "display_width": null,
                "locked": false,
                "required": false,
                "default": {
                  "color": "#FFFFFF"
                }
              }
            ],
            "display_width": null,
            "locked": false,
            "tab": "CONTENT",
            "expanded": false,
            "required": false
          },
          {
            "label": "Background",
            "name": "background",
            "type": "group",
            "children": [
              {
                "label": "Color",
                "name": "color",
                "type": "color",
                "visibility": {
                  "hidden_subfields": {
                    "opacity": true
                  }
                },
                "display_width": null,
                "locked": false,
                "required": false,
                "inherited_value": {
                  "property_value_paths": {
                    "color": "theme.global_colors.primary.color"
                  }
                },
                "default": {
                  "color": null,
                  "opacity": null
                }
              }
            ],
            "display_width": null,
            "locked": false,
            "tab": "CONTENT",
            "expanded": false,
            "required": false
          }
        ],
        "display_width": null,
        "locked": false,
        "tab": "CONTENT",
        "expanded": false,
        "required": false
      },
      {
        "label": "Body",
        "name": "table_body",
        "type": "group",
        "children": [
          {
            "label": "Text",
            "name": "text",
            "type": "group",
            "children": [
              {
                "label": "Color",
                "name": "color",
                "type": "color",
                "visibility": {
                  "hidden_subfields": {
                    "opacity": true
                  }
                },
                "display_width": null,
                "locked": false,
                "required": false,
                "inherited_value": {
                  "property_value_paths": {
                    "color": "theme.global_fonts.primary.color"
                  }
                },
                "default": {
                  "color": null,
                  "opacity": null
                }
              }
            ],
            "display_width": null,
            "locked": false,
            "tab": "CONTENT",
            "expanded": false,
            "required": false
          },
          {
            "label": "Background",
            "name": "background",
            "type": "group",
            "children": [
              {
                "label": "Color",
                "name": "color",
                "type": "color",
                "display_width": null,
                "locked": false,
                "required": false,
                "default": {
                  "color": "#FFFFFF",
                  "opacity": 100
                }
              }
            ],
            "display_width": null,
            "locked": false,
            "tab": "CONTENT",
            "expanded": false,
            "required": false
          }
        ],
        "display_width": null,
        "locked": false,
        "tab": "CONTENT",
        "expanded": false,
        "required": false
      },
      {
        "label": "Footer",
        "name": "footer",
        "type": "group",
        "children": [
          {
            "label": "Text",
            "name": "text",
            "type": "group",
            "children": [
              {
                "label": "Color",
                "name": "color",
                "type": "color",
                "visibility": {
                  "hidden_subfields": {
                    "opacity": true
                  }
                },
                "display_width": null,
                "locked": false,
                "required": false,
                "inherited_value": {
                  "property_value_paths": {
                    "color": "theme.global_fonts.primary.color"
                  }
                },
                "default": {
                  "color": null,
                  "opacity": null
                }
              }
            ],
            "display_width": null,
            "locked": false,
            "tab": "CONTENT",
            "expanded": false,
            "required": false
          },
          {
            "label": "Background",
            "name": "background",
            "type": "group",
            "children": [
              {
                "label": "Color",
                "name": "color",
                "type": "color",
                "display_width": null,
                "locked": false,
                "required": false,
                "default": {
                  "color": "#FFFFFF",
                  "opacity": 100
                }
              }
            ],
            "display_width": null,
            "locked": false,
            "tab": "CONTENT",
            "expanded": false,
            "required": false
          }
        ],
        "display_width": null,
        "locked": false,
        "tab": "CONTENT",
        "expanded": false,
        "required": false
      },
      {
        "label": "Cells",
        "name": "cells",
        "type": "group",
        "children": [
          {
            "label": "Spacing",
            "name": "spacing",
            "type": "group",
            "children": [
              {
                "label": "Spacing",
                "name": "spacing",
                "type": "spacing",
                "visibility": {
                  "hidden_subfields": {
                    "margin": true
                  }
                },
                "display_width": null,
                "locked": false,
                "required": false,
                "default": {
                  "padding": {
                    "top": {
                      "value": 18,
                      "units": "px"
                    },
                    "right": {
                      "value": 18,
                      "units": "px"
                    },
                    "bottom": {
                      "value": 18,
                      "units": "px"
                    },
                    "left": {
                      "value": 18,
                      "units": "px"
                    }
                  }
                }
              }
            ],
            "display_width": null,
            "locked": false,
            "tab": "CONTENT",
            "expanded": false,
            "required": false
          },
          {
            "label": "Border",
            "name": "border",
            "type": "group",
            "children": [
              {
                "label": "Border",
                "name": "border",
                "type": "border",
                "allow_custom_border_sides": false,
                "display_width": null,
                "locked": false,
                "required": false,
                "inherited_value": {
                  "property_value_paths": {
                    "bottom.color": "theme.global_fonts.primary.color",
                    "left.color": "theme.global_fonts.primary.color",
                    "right.color": "theme.global_fonts.primary.color",
                    "top.color": "theme.global_fonts.primary.color"
                  }
                },
                "default": {
                  "top": {
                    "width": {
                      "value": 1,
                      "units": "px"
                    },
                    "opacity": 100,
                    "style": "solid",
                    "color": "#494A52"
                  },
                  "right": {
                    "width": {
                      "value": 1,
                      "units": "px"
                    },
                    "opacity": 100,
                    "style": "solid",
                    "color": "#494A52"
                  },
                  "bottom": {
                    "width": {
                      "value": 1,
                      "units": "px"
                    },
                    "opacity": 100,
                    "style": "solid",
                    "color": "#494A52"
                  },
                  "left": {
                    "width": {
                      "value": 1,
                      "units": "px"
                    },
                    "opacity": 100,
                    "style": "solid",
                    "color": "#494A52"
                  }
                }
              }
            ],
            "display_width": null,
            "locked": false,
            "tab": "CONTENT",
            "expanded": false,
            "required": false
          }
        ],
        "display_width": null,
        "locked": false,
        "tab": "CONTENT",
        "expanded": false,
        "required": false
      }
    ],
    "display_width": null,
    "locked": false,
    "tab": "CONTENT",
    "expanded": false,
    "required": false
  },
  {
    "label": "Website header",
    "name": "header",
    "type": "group",
    "children": [
      {
        "label": "Menu",
        "name": "menu",
        "type": "group",
        "children": [
          {
            "label": "Text",
            "name": "text",
            "type": "group",
            "children": [
              {
                "label": "Color",
                "name": "color",
                "type": "color",
                "visibility": {
                  "hidden_subfields": {
                    "opacity": true
                  }
                },
                "display_width": null,
                "locked": false,
                "required": false,
                "default": {
                  "color": "#FFFFFF",
                  "opacity": 100
                }
              }
            ],
            "display_width": null,
            "locked": false,
            "tab": "CONTENT",
            "expanded": false,
            "required": false,
            "default": {
              "color": {
                "color": "#FFFFFF",
                "opacity": 100
              }
            }
          },
          {
            "label": "Drop downs",
            "name": "drop_downs",
            "type": "group",
            "children": [
              {
                "label": "Text",
                "name": "text",
                "type": "group",
                "children": [
                  {
                    "label": "Color",
                    "name": "color",
                    "type": "color",
                    "visibility": {
                      "hidden_subfields": {
                        "opacity": true
                      }
                    },
                    "display_width": null,
                    "locked": false,
                    "required": false,
                    "inherited_value": {
                      "property_value_paths": {
                        "color": "theme.global_fonts.primary.color"
                      }
                    },
                    "default": {
                      "color": null,
                      "opacity": null
                    }
                  }
                ],
                "display_width": null,
                "locked": false,
                "tab": "CONTENT",
                "expanded": false,
                "required": false
              },
              {
                "label": "Background",
                "name": "background",
                "type": "group",
                "children": [
                  {
                    "label": "Color",
                    "name": "color",
                    "type": "color",
                    "visibility": {
                      "hidden_subfields": {
                        "opacity": true
                      }
                    },
                    "display_width": null,
                    "locked": false,
                    "required": false,
                    "inherited_value": {
                      "property_value_paths": {
                        "color": "theme.global_colors.primary.color"
                      }
                    },
                    "default": {
                      "color": null,
                      "opacity": null
                    }
                  }
                ],
                "display_width": null,
                "locked": false,
                "tab": "CONTENT",
                "expanded": false,
                "required": false
              },
              {
                "label": "Border",
                "name": "border",
                "type": "group",
                "children": [
                  {
                    "label": "Border",
                    "name": "border",
                    "type": "border",
                    "allow_custom_border_sides": false,
                    "display_width": null,
                    "locked": false,
                    "required": false,
                    "inherited_value": {
                      "property_value_paths": {
                        "bottom.color": "theme.global_colors.primary.color",
                        "left.color": "theme.global_colors.primary.color",
                        "right.color": "theme.global_colors.primary.color",
                        "top.color": "theme.global_colors.primary.color"
                      }
                    },
                    "default": {
                      "top": {
                        "width": {
                          "value": 2,
                          "units": "px"
                        },
                        "opacity": 100,
                        "style": "solid",
                        "color": "#494A52"
                      },
                      "right": {
                        "width": {
                          "value": 2,
                          "units": "px"
                        },
                        "opacity": 100,
                        "style": "solid",
                        "color": "#494A52"
                      },
                      "bottom": {
                        "width": {
                          "value": 2,
                          "units": "px"
                        },
                        "opacity": 100,
                        "style": "solid",
                        "color": "#494A52"
                      },
                      "left": {
                        "width": {
                          "value": 2,
                          "units": "px"
                        },
                        "opacity": 100,
                        "style": "solid",
                        "color": "#494A52"
                      }
                    }
                  }
                ],
                "display_width": null,
                "locked": false,
                "tab": "CONTENT",
                "expanded": false,
                "required": false
              }
            ],
            "display_width": null,
            "locked": false,
            "tab": "CONTENT",
            "expanded": false,
            "required": false
          }
        ],
        "display_width": null,
        "locked": false,
        "tab": "CONTENT",
        "expanded": false,
        "required": false,
        "default": {
          "text": {
            "color": {
              "color": "#FFFFFF",
              "opacity": 100
            }
          }
        }
      },
      {
        "label": "Background",
        "name": "background",
        "type": "group",
        "children": [
          {
            "label": "Color",
            "name": "color",
            "type": "color",
            "visibility": {
              "hidden_subfields": {
                "opacity": true
              }
            },
            "display_width": null,
            "locked": false,
            "required": false,
            "inherited_value": {
              "property_value_paths": {
                "color": "theme.global_colors.primary.color"
              }
            },
            "default": {
              "color": null,
              "opacity": null
            }
          }
        ],
        "display_width": null,
        "locked": false,
        "tab": "CONTENT",
        "expanded": false,
        "required": false
      }
    ],
    "display_width": null,
    "locked": false,
    "tab": "CONTENT",
    "expanded": false,
    "required": false,
    "default": {
      "menu": {
        "text": {
          "color": {
            "color": "#FFFFFF",
            "opacity": 100
          }
        }
      }
    }
  },
  {
    "label": "Website footer",
    "name": "footer",
    "type": "group",
    "children": [
      {
        "label": "Text",
        "name": "text",
        "type": "group",
        "children": [
          {
            "label": "Color",
            "name": "color",
            "type": "color",
            "visibility": {
              "hidden_subfields": {
                "opacity": true
              }
            },
            "display_width": null,
            "locked": false,
            "required": false,
            "inherited_value": {
              "property_value_paths": {
                "color": "theme.global_fonts.primary.color"
              }
            },
            "default": {
              "color": null,
              "opacity": null
            }
          }
        ],
        "display_width": null,
        "locked": false,
        "tab": "CONTENT",
        "expanded": false,
        "required": false
      },
      {
        "label": "Background",
        "name": "background",
        "type": "group",
        "children": [
          {
            "label": "Color",
            "name": "color",
            "type": "color",
            "display_width": null,
            "locked": false,
            "required": false,
            "inherited_value": {
              "property_value_paths": {
                "color": "theme.global_colors.secondary.color"
              }
            },
            "default": {
              "opacity": 100
            }
          }
        ],
        "display_width": null,
        "locked": false,
        "tab": "CONTENT",
        "expanded": false,
        "required": false
      }
    ],
    "display_width": null,
    "locked": false,
    "tab": "CONTENT",
    "expanded": false,
    "required": false
  }
]